{"author": "Sambre", "channel": "demo-sambre", "content": "!symptomes"}
{"author": "Sambre", "channel": "demo-sambre", "content": "oui"}
{"author": "Sambre", "channel": "demo-sambre", "content": "non"}
{"author": "Sambre", "channel": "demo-sambre", "content": "!speak livres"}
{"author": "Sambre", "channel": "demo-sambre", "content": "!speak luca"}
{"author": "Sambre", "channel": "demo-sambre", "content": "!recommandations"}
{"author": "Sambre", "channel": "demo-sambre", "content": "films*"}
{"author": "Sambre", "channel": "demo-sambre", "content": "films"}
{"author": "Sambre", "channel": "demo-sambre", "content": "!recommandations"}
{"author": "Sambre", "channel": "demo-sambre", "content": "films"}
{"author": "Sambre", "channel": "demo-sambre", "content": "science-fiction"}
{"author": "Sambre", "channel": "demo-sambre", "content": "non"}
{"author": "Sambre", "channel": "demo-sambre", "content": "!lastcommand"}
{"author": "Sambre", "channel": "demo-sambre", "content": "!commandall"}
{"author": "Sambre", "channel": "demo-sambre", "content": "!command_user 322915910979551233"}
{"author": "Sambre", "channel": "demo-sambre", "content": "!commanduser 322915910979551233"}
{"author": "Sambre", "channel": "demo-sambre", "content": "!historique 322915910979551233"}
{"author": "Sambre", "channel": "demo-sambre", "content": "!commanduser 1091253101069086741"}
{"author": "Sambre", "channel": "demo-sambre", "content": "!clearcommand"}
{"author": "Sambre", "channel": "demo-sambre", "content": "!commanduser 322915910979551233"}
{"author": "Sambre", "channel": "demo-sambre", "content": "!symptomes"}
{"author": "Sambre", "channel": "demo-sambre", "content": "non"}
{"author": "Sambre", "channel": "demo-sambre", "content": "non"}
{"author": "PyBot", "channel": "flood-sambre", "content": ""}
{"author": "Tot0p", "channel": "flood-sambre", "content": "uwu"}
{"author": "PyBot", "channel": "flood-sambre", "content": ""}
{"author": "PyBot", "channel": "flood-sambre", "content": ""}
{"author": "PyBot", "channel": "flood-sambre", "content": ""}
